btg_investment_flow_portfolio_optimization/__init__.py
btg_investment_flow_portfolio_optimization/btg_api.py
btg_investment_flow_portfolio_optimization/portfolio_optimization.py
btg_investment_flow_portfolio_optimization/standard.py
btg_investment_flow_portfolio_optimization-0.0.2.dist-info/METADATA
btg_investment_flow_portfolio_optimization-0.0.2.dist-info/WHEEL
btg_investment_flow_portfolio_optimization-0.0.2.dist-info/RECORD
