Metadata-Version: 2.1
Name: btg-investment-flow-portfolio-optimization
Version: 0.0.2
Summary: 
Author: NG.CASH
Requires-Python: >=3.8,<4.0
Classifier: Programming Language :: Python :: 3
Classifier: Programming Language :: Python :: 3.8
Classifier: Programming Language :: Python :: 3.9
Classifier: Programming Language :: Python :: 3.10
Classifier: Programming Language :: Python :: 3.11
Requires-Dist: boto3 (==1.26.135)
Requires-Dist: pandas (>=2.0,<3.0)
Requires-Dist: pytest (>=6.2,<7.0)
Requires-Dist: pytest-cov (==4.0.0)
